bitcoin_utxo_lp/__init__.py
bitcoin_utxo_lp/model.py
bitcoin_utxo_lp/solver.py
bitcoin_utxo_lp/types.py
bitcoin_utxo_lp-0.1.0.dist-info/METADATA
bitcoin_utxo_lp-0.1.0.dist-info/WHEEL
bitcoin_utxo_lp-0.1.0.dist-info/RECORD
