Metadata-Version: 2.4
Name: bitcoin-utxo-lp
Version: 0.1.0
Summary: 
Author: Antonio Ventilii
Requires-Python: >=3.11
Classifier: Programming Language :: Python :: 3
Classifier: Programming Language :: Python :: 3.11
Classifier: Programming Language :: Python :: 3.12
Classifier: Programming Language :: Python :: 3.13
Classifier: Programming Language :: Python :: 3.14
Requires-Dist: pulp (>=3.3.0,<4.0.0)
